finny_scraper/__init__.py
finny_scraper/finny_scraper.py
finny_scraper-0.9.dist-info/METADATA
finny_scraper-0.9.dist-info/WHEEL
finny_scraper-0.9.dist-info/top_level.txt
finny_scraper-0.9.dist-info/RECORD
