Metadata-Version: 2.1
Name: finny-scraper
Version: 0.9
Summary: A package for scraping property information from Finny website
Home-page: https://github.com/samueltanner/rfin_scraper
Classifier: Programming Language :: Python :: 3
Classifier: License :: OSI Approved :: MIT License
Classifier: Operating System :: OS Independent
Requires-Dist: beautifulsoup4
Requires-Dist: requests
